src/snf2json/__init__.py
src/snf2json/snf2json.py
snf2json-0.1.dist-info/LICENSE
snf2json-0.1.dist-info/METADATA
snf2json-0.1.dist-info/WHEEL
snf2json-0.1.dist-info/entry_points.txt
snf2json-0.1.dist-info/top_level.txt
snf2json-0.1.dist-info/RECORD
