Metadata-Version: 2.1
Name: snf2json
Version: 0.1
Summary: A convertion tool for Sniffles objects (SNF) to JSON like objects (SNFJ)
Home-page: https://github.com/philippesanio/snf2json
Author: Philippe Sanio
Author-email: philippe.sanio@gmail.com
License: MIT
License-File: LICENSE
Requires-Dist: sniffles >=2.2
